serverseeker.py
serverseeker-1.0.2.dist-info/LICENSE
serverseeker-1.0.2.dist-info/METADATA
serverseeker-1.0.2.dist-info/WHEEL
serverseeker-1.0.2.dist-info/top_level.txt
serverseeker-1.0.2.dist-info/RECORD
