Metadata-Version: 2.1
Name: serverseeker
Version: 1.0.2
Summary: A Python wrapper for the ServerSeeker API. This is a CLI to work with ServerSeeker, a tool to scan for Minecraft servers. Visit serverseeker.net for more info.
Author-email: Igyeom Park <hi@ians.site>
Project-URL: GitHub Repo, https://github.com/Igyeom/ServerSeeker
Project-URL: ServerSeeker Discord, https://serverseeker.net
Project-URL: ServerSeeker Documentation, https://serverseeker.net/docs
Classifier: Programming Language :: Python :: 3
Classifier: License :: OSI Approved :: MIT License
Classifier: Operating System :: OS Independent
Requires-Python: >=3.7
License-File: LICENSE
